numcodecs_wasm_qpet_sperr/__init__.py
numcodecs_wasm_qpet_sperr/__init__.pyi
numcodecs_wasm_qpet_sperr/codec.wasm
numcodecs_wasm_qpet_sperr/py.typed
numcodecs_wasm_qpet_sperr-0.2.0.dist-info/METADATA
numcodecs_wasm_qpet_sperr-0.2.0.dist-info/WHEEL
numcodecs_wasm_qpet_sperr-0.2.0.dist-info/entry_points.txt
numcodecs_wasm_qpet_sperr-0.2.0.dist-info/top_level.txt
numcodecs_wasm_qpet_sperr-0.2.0.dist-info/RECORD
